LICENSE.txt
MANIFEST.in
README.rst
setup.py
Mopidy_Simple_Webclient.egg-info/PKG-INFO
Mopidy_Simple_Webclient.egg-info/SOURCES.txt
Mopidy_Simple_Webclient.egg-info/dependency_links.txt
Mopidy_Simple_Webclient.egg-info/entry_points.txt
Mopidy_Simple_Webclient.egg-info/not-zip-safe
Mopidy_Simple_Webclient.egg-info/requires.txt
Mopidy_Simple_Webclient.egg-info/top_level.txt
mopidy_simple_webclient/__init__.py
mopidy_simple_webclient/ext.conf
mopidy_simple_webclient/static/index.html
mopidy_simple_webclient/static/behavior/client.js
mopidy_simple_webclient/static/behavior/sprintf.js
mopidy_simple_webclient/static/images/eject.png
mopidy_simple_webclient/static/images/next.png
mopidy_simple_webclient/static/images/pause.png
mopidy_simple_webclient/static/images/play.png
mopidy_simple_webclient/static/images/previous.png
mopidy_simple_webclient/static/images/repeat.png
mopidy_simple_webclient/static/images/shuffle.png
mopidy_simple_webclient/static/images/spinner.gif
mopidy_simple_webclient/static/images/stop.png
mopidy_simple_webclient/static/styles/client.css