Metadata-Version: 1.1
Name: Mopidy-Simple-Webclient
Version: 0.1
Summary: Very simple and mobile friendly web interface for the Mopidy music server
Home-page: https://github.com/xolox/mopidy-simple-webclient
Author: Peter Odding
Author-email: peter@peterodding.com
License: UNKNOWN
Platform: UNKNOWN
Classifier: Environment :: No Input/Output (Daemon)
Classifier: Intended Audience :: End Users/Desktop
Classifier: License :: OSI Approved :: MIT License
Classifier: Operating System :: OS Independent
Classifier: Programming Language :: Python :: 2
Classifier: Topic :: Multimedia :: Sound/Audio :: Players
